langchain_aws/__init__.py
langchain_aws/function_calling.py
langchain_aws/py.typed
langchain_aws/utils.py
langchain_aws/agents/__init__.py
langchain_aws/agents/base.py
langchain_aws/agents/types.py
langchain_aws/agents/utils.py
langchain_aws/chains/__init__.py
langchain_aws/chains/graph_qa/__init__.py
langchain_aws/chains/graph_qa/neptune_cypher.py
langchain_aws/chains/graph_qa/neptune_sparql.py
langchain_aws/chains/graph_qa/prompts.py
langchain_aws/chat_models/__init__.py
langchain_aws/chat_models/_compat.py
langchain_aws/chat_models/bedrock.py
langchain_aws/chat_models/bedrock_converse.py
langchain_aws/chat_models/sagemaker_endpoint.py
langchain_aws/data/__init__.py
langchain_aws/data/_profiles.py
langchain_aws/data/profile_augmentations.toml
langchain_aws/document_compressors/__init__.py
langchain_aws/document_compressors/rerank.py
langchain_aws/embeddings/__init__.py
langchain_aws/embeddings/bedrock.py
langchain_aws/graphs/__init__.py
langchain_aws/graphs/neptune_graph.py
langchain_aws/graphs/neptune_rdf_graph.py
langchain_aws/llms/__init__.py
langchain_aws/llms/bedrock.py
langchain_aws/llms/sagemaker_endpoint.py
langchain_aws/retrievers/__init__.py
langchain_aws/retrievers/bedrock.py
langchain_aws/retrievers/kendra.py
langchain_aws/retrievers/s3_vectors.py
langchain_aws/runnables/__init__.py
langchain_aws/runnables/q_business.py
langchain_aws/tools/__init__.py
langchain_aws/tools/browser_session_manager.py
langchain_aws/tools/browser_toolkit.py
langchain_aws/tools/browser_tools.py
langchain_aws/tools/code_interpreter_toolkit.py
langchain_aws/tools/nova_tools.py
langchain_aws/tools/utils.py
langchain_aws/utilities/math.py
langchain_aws/utilities/redis.py
langchain_aws/utilities/utils.py
langchain_aws/vectorstores/__init__.py
langchain_aws/vectorstores/inmemorydb/__init__.py
langchain_aws/vectorstores/inmemorydb/base.py
langchain_aws/vectorstores/inmemorydb/cache.py
langchain_aws/vectorstores/inmemorydb/constants.py
langchain_aws-1.2.2.dist-info/METADATA
langchain_aws-1.2.2.dist-info/WHEEL
langchain_aws-1.2.2.dist-info/licenses/LICENSE
langchain_aws-1.2.2.dist-info/RECORD
