Metadata-Version: 2.4
Name: langchain-aws
Version: 1.2.2
Summary: An integration package connecting AWS and LangChain
Project-URL: Source Code, https://github.com/langchain-ai/langchain-aws/tree/main/libs/aws
Project-URL: Repository, https://github.com/langchain-ai/langchain-aws
License: MIT
License-File: LICENSE
Requires-Python: >=3.10
Requires-Dist: boto3>=1.42.5
Requires-Dist: langchain-core>=1.2.5
Requires-Dist: numpy<3,>=1.0.0; python_version < '3.12'
Requires-Dist: numpy<3,>=2.2; python_version >= '3.12'
Requires-Dist: pydantic<3,>=2.10.6
Provides-Extra: tools
Requires-Dist: beautifulsoup4>=4.13.4; extra == 'tools'
Requires-Dist: bedrock-agentcore>=1.2.0; (python_version >= '3.10') and extra == 'tools'
Requires-Dist: playwright>=1.53.0; extra == 'tools'
